mlflow_cynex/__init__.py
mlflow_cynex/cli.py
mlflow_cynex/logging.py
mlflow_cynex-0.1.2.dist-info/METADATA
mlflow_cynex-0.1.2.dist-info/WHEEL
mlflow_cynex-0.1.2.dist-info/entry_points.txt
mlflow_cynex-0.1.2.dist-info/RECORD
