Metadata-Version: 2.4
Name: mlflow-cynex
Version: 0.1.2
Summary: Cynex trajectory viewer integration for MLflow
Project-URL: Homepage, https://github.com/user/cynex
Project-URL: Documentation, https://github.com/user/cynex#readme
Project-URL: Repository, https://github.com/user/cynex
Project-URL: Issues, https://github.com/user/cynex/issues
Author: Cynex Team
License-Expression: MIT
Keywords: cybersecurity,mlflow,reinforcement-learning,trajectories,visualization
Classifier: Development Status :: 4 - Beta
Classifier: Environment :: Console
Classifier: Intended Audience :: Developers
Classifier: Intended Audience :: Science/Research
Classifier: License :: OSI Approved :: MIT License
Classifier: Operating System :: OS Independent
Classifier: Programming Language :: Python :: 3
Classifier: Programming Language :: Python :: 3.9
Classifier: Programming Language :: Python :: 3.10
Classifier: Programming Language :: Python :: 3.11
Classifier: Programming Language :: Python :: 3.12
Classifier: Topic :: Scientific/Engineering :: Artificial Intelligence
Classifier: Topic :: Scientific/Engineering :: Visualization
Requires-Python: >=3.9
Requires-Dist: mlflow>=2.0.0
